Metadata-Version: 1.0
Name: arXiv-download
Version: 0.1
Summary: View, Get Info and Download research papers from arxiv.org on your terminal!!
Home-page: https://github.com/pvskand/arXiv_download
Author: Skand Vishwanath Peri
Author-email: pvskand@gmail.com
License: MIT
Platform: UNKNOWN
